fileformats/testing/__init__.py
fileformats/testing/_version.py
fileformats/testing/basic.py
fileformats/testing/classifiers.py
fileformats/testing/converters.py
fileformats/testing/headers.py
fileformats_testing-0.3.1.dist-info/METADATA
fileformats_testing-0.3.1.dist-info/WHEEL
fileformats_testing-0.3.1.dist-info/licenses/LICENSE
fileformats_testing-0.3.1.dist-info/RECORD
